setup.py
ngrok/__init__.py
ngrok/client.py
ngrok/link.py
python3_ngrok.egg-info/PKG-INFO
python3_ngrok.egg-info/SOURCES.txt
python3_ngrok.egg-info/dependency_links.txt
python3_ngrok.egg-info/top_level.txt