Metadata-Version: 1.0
Name: python3-ngrok
Version: 0.2
Summary: Python 3 bindings for ngrok local and Link APIs
Home-page: https://github.com/vintasoftware/python3-ngrok
Author: Jacob Cook <jacob@coderouge.co>, Flávio Juvenal <flavio@vinta.com.br>
Author-email: flavio@vinta.com.br
License: GPLv3
Platform: UNKNOWN
